LAB1/task2/equality.v
module equality(input [3:0]A, input [3:0]B, output Y);

assign Y = (A == B) ? 1 : 0;

endmodule

LAB1/task2/tb.v
`timescale 1ns / 1ns
module tb;

reg [3:0] A, B;
wire Y;

equality dut(.A(A), .B(B), .Y(Y));

initial begin
    $dumpfile("equality.vcd");
    $dumpvars(0, tb);

    A = 4'd0; B = 4'd0; 
    #10;  
    A = 4'd12; B = 4'd12; 
    #10;  
    A = 4'd11; B = 4'd9; 
    #10;  
    A = 4'd13; B = 4'd10; 
    #10;
    A = 4'd11; B = 4'd11;
    #10;
    A = 4'd4; B = 4'd5;
    #10;
    A = 4'd9; B = 4'd15;
    #10;
    A = 4'd5; B = 4'd5;
    #10;

    $finish;

end

endmodule

LAB1/task2/equality.vcd
$date
	Wed Jul 30 20:55:57 2025
$end
$version
	Icarus Verilog
$end
$timescale
	1ns
$end
$scope module tb $end
$var wire 1 ! Y $end
$var reg 4 " A [3:0] $end
$var reg 4 # B [3:0] $end
$scope module dut $end
$var wire 4 $ A [3:0] $end
$var wire 4 % B [3:0] $end
$var wire 1 ! Y $end
$upscope $end
$upscope $end
$enddefinitions $end
$comment Show the parameter values. $end
$dumpall
$end
#0
$dumpvars
b0 %
b0 $
b0 #
b0 "
1!
$end
#10
b1100 #
b1100 %
b1100 "
b1100 $
#20
0!
b1001 #
b1001 %
b1011 "
b1011 $
#30
b1010 #
b1010 %
b1101 "
b1101 $
#40
1!
b1011 #
b1011 %
b1011 "
b1011 $
#50
0!
b101 #
b101 %
b100 "
b100 $
#60
b1111 #
b1111 %
b1001 "
b1001 $
#70
1!
b101 #
b101 %
b101 "
b101 $
