fsm-assignments(LAB2)/problem3_vending/vending_mealy.v
module vending_mealy(
input wire clk,
input wire rst, // sync active-high
input wire [1:0] coin, // 01=5, 10=10, 00=idle
output wire dispense,// 1-cycle pulse
output wire chg5 // 1-cycle pulse when returning 5
);

reg [2:0] state_present, state_next;
reg x, y; // temporary reg type to hold dispense and change value for one cycle, x for dispense and y for change

parameter init = 3'b000;
parameter five = 3'b001;
parameter ten = 3'b010;
parameter fifteen = 3'b011;

always @(posedge clk) begin
    if(rst) state_present <= init;
    else state_present <= state_next;
end

always @(*) begin
    case(state_present)
        init: begin
            if(coin == 2'b01) state_next = five;
            else if (coin == 2'b10) state_next = ten;
            else state_next = state_present;
        end
        five: begin
            if(coin == 2'b01) state_next = ten;
            else if (coin == 2'b10) state_next = fifteen;
            else state_next = state_present;
        end
        ten: begin
            if(coin == 2'b01) state_next = fifteen;
            else if (coin == 2'b10) state_next = init;
            else state_next = state_present;
        end
        fifteen: begin
            if(coin == 2'b01) state_next = init;
            else if (coin == 2'b10) state_next = init;
            else state_next = state_present;
        end
        default: state_next = state_present;
    endcase
end

always @(posedge clk) begin
    if (rst) begin
        x <= 1'b0;
        y     <= 1'b0;
    end else begin
        x <= 1'b0;
        y    <= 1'b0;

        if ((state_present == ten     && coin == 2'b10) || 
            (state_present == fifteen && (coin == 2'b01 || coin == 2'b10)))
            x <= 1'b1;

        if (state_present == fifteen && coin == 2'b10)
            y <= 1'b1;
    end
end

assign dispense = x;
assign chg5 = y;


endmodule

fsm-assignments(LAB2)/problem3_vending/tb_vending_mealy.v
`timescale 1ms/1ms

module tb_vending_mealy;
reg clk, rst;
reg [1:0] coin;
wire dispense, chg5;

vending_mealy dut(.clk(clk), .rst(rst), .coin(coin),
.dispense(dispense), .chg5(chg5));

initial begin
    clk = 0;
end
always #5 clk = ~clk;

initial begin
    $dumpfile("vending.vcd");
    $dumpvars(0, tb_vending_mealy);
    
    rst = 1;
    coin = 2'b00;
    #12;
    rst = 0;
    
    @(negedge clk); coin = 2'b01;
    @(negedge clk); coin = 2'b00;
    @(negedge clk); coin = 2'b01;
    @(negedge clk); coin = 2'b00;
    @(negedge clk); coin = 2'b10;

    @(negedge clk); coin = 2'b00;

    @(negedge clk); coin = 2'b01;
    @(negedge clk); coin = 2'b00;
    @(negedge clk); coin = 2'b10;
    @(negedge clk); coin = 2'b00;
    @(negedge clk); coin = 2'b10;

    @(negedge clk); coin = 2'b00;

    @(negedge clk); coin = 2'b10;
    @(negedge clk); coin = 2'b00;
    @(negedge clk); coin = 2'b01;
    @(negedge clk); coin = 2'b00;
    @(negedge clk); coin = 2'b01;

    @(negedge clk); coin = 2'b00;

    #100;

    $finish;

end

endmodule

fsm-assignments(LAB2)/problem3_vending/vending.vcd
$date
	Tue Aug 19 12:30:01 2025
$end
$version
	Icarus Verilog
$end
$timescale
	1ms
$end
$scope module tb_vending_mealy $end
$var wire 1 ! dispense $end
$var wire 1 " chg5 $end
$var reg 1 # clk $end
$var reg 2 $ coin [1:0] $end
$var reg 1 % rst $end
$scope module dut $end
$var wire 1 " chg5 $end
$var wire 1 # clk $end
$var wire 2 & coin [1:0] $end
$var wire 1 ! dispense $end
$var wire 1 % rst $end
$var parameter 3 ' fifteen $end
$var parameter 3 ( five $end
$var parameter 3 ) init $end
$var parameter 3 * ten $end
$var reg 3 + state_next [2:0] $end
$var reg 3 , state_present [2:0] $end
$var reg 1 - x $end
$var reg 1 . y $end
$upscope $end
$upscope $end
$enddefinitions $end
$comment Show the parameter values. $end
$dumpall
b10 *
b0 )
b1 (
b11 '
$end
#0
$dumpvars
x.
x-
bx ,
bx +
b0 &
1%
b0 $
0#
x"
x!
$end
#5
b0 +
b0 ,
0"
0.
0!
0-
1#
#10
0#
#12
0%
#15
1#
#20
b1 +
b1 $
b1 &
0#
#25
b10 +
b1 ,
1#
#30
b1 +
b0 $
b0 &
0#
#35
1#
#40
b10 +
b1 $
b1 &
0#
#45
b11 +
b10 ,
1#
#50
b10 +
b0 $
b0 &
0#
#55
1#
#60
b0 +
b10 $
b10 &
0#
#65
b10 +
b0 ,
1!
1-
1#
#70
b0 +
b0 $
b0 &
0#
#75
0!
0-
1#
#80
b1 +
b1 $
b1 &
0#
#85
b10 +
b1 ,
1#
#90
b1 +
b0 $
b0 &
0#
#95
1#
#100
b11 +
b10 $
b10 &
0#
#105
b0 +
b11 ,
1#
#110
b11 +
b0 $
b0 &
0#
#115
1#
#120
b0 +
b10 $
b10 &
0#
#125
b10 +
b0 ,
1"
1.
1!
1-
1#
#130
b0 +
b0 $
b0 &
0#
#135
0"
0.
0!
0-
1#
#140
b10 +
b10 $
b10 &
0#
#145
b0 +
b10 ,
1#
#150
b10 +
b0 $
b0 &
0#
#155
1#
#160
b11 +
b1 $
b1 &
0#
#165
b0 +
b11 ,
1#
#170
b11 +
b0 $
b0 &
0#
#175
1#
#180
b0 +
b1 $
b1 &
0#
#185
b1 +
b0 ,
1!
1-
1#
#190
b0 +
b0 $
b0 &
0#
#195
0!
0-
1#
