fsm-assignments(LAB2)/problem1_seqdet/seq_det_mealy.v
module seq_detect_mealy(
    input wire clk,
    input wire rst,
    input wire din,
    output wire y);

    reg [1:0] state_present, state_next;

    parameter init = 2'b00;
    parameter one = 2'b01;
    parameter two = 2'b10;
    parameter three = 2'b11;

    always @(posedge clk)
    begin
        if(rst) state_present <= init;
        else state_present <= state_next;
    end
    always @(*)
    begin
        case(state_present)
            init: begin
                if(din) state_next = one;
                else state_next = init;
            end
            one: begin
                if(din) state_next = two;
                else state_next = init;
            end
            two: begin
                if(din) state_next = two;
                else state_next = three;
            end
            three: begin
                if(din) state_next = one;
                else state_next = init;
            end
            default: state_next = init;
        endcase
    end
    assign y = (state_present == three)&&din;
endmodule

fsm-assignments(LAB2)/problem1_seqdet/tb_seq_det_mealy.v
module tb_seq_detect_mealy;
reg clk, rst, din;
wire y;

seq_detect_mealy dut(.clk(clk), .rst(rst), .din(din), .y(y));

initial begin
    clk = 0;
end
always #5 clk = ~clk;

initial begin
    $dumpfile("dump.vcd");
    $dumpvars(0, tb_seq_detect_mealy);

    rst = 1;
    din = 0;

    #12;
    
    rst = 0;
    @(negedge clk); din = 1;
    @(negedge clk); din = 1;
    @(negedge clk); din = 0;
    @(negedge clk); din = 1;
    @(negedge clk); din = 1;
    @(negedge clk); din = 0;
    @(negedge clk); din = 1;
    @(negedge clk); din = 0;
    @(negedge clk); din = 1;
    @(negedge clk); din = 1;
    @(negedge clk); din = 0;
    @(negedge clk); din = 1;
    @(negedge clk); din = 1;
    @(negedge clk); din = 0;
    @(negedge clk); din = 1;
    @(negedge clk); din = 0;

    #20;
    $finish;

end
endmodule

fsm-assignments(LAB2)/problem1_seqdet/sequence2.vcd
$date
	Sat Aug 16 17:57:40 2025
$end
$version
	Icarus Verilog
$end
$timescale
	1s
$end
$scope module tb_seq_detect_mealy $end
$var wire 1 ! y $end
$var reg 1 " clk $end
$var reg 1 # din $end
$var reg 1 $ rst $end
$scope module dut $end
$var wire 1 " clk $end
$var wire 1 # din $end
$var wire 1 $ rst $end
$var wire 1 ! y $end
$var parameter 2 % init $end
$var parameter 2 & one $end
$var parameter 2 ' three $end
$var parameter 2 ( two $end
$var reg 2 ) state_next [1:0] $end
$var reg 2 * state_present [1:0] $end
$upscope $end
$upscope $end
$enddefinitions $end
$comment Show the parameter values. $end
$dumpall
b10 (
b11 '
b1 &
b0 %
$end
#0
$dumpvars
bx *
b0 )
1$
0#
0"
0!
$end
#5
b0 *
1"
#10
0"
#12
0$
#15
1"
#20
b1 )
1#
0"
#25
b10 )
b1 *
1"
#30
0"
#35
b10 *
1"
#40
b11 )
0#
0"
#45
b0 )
b11 *
1"
#50
1!
b1 )
1#
0"
#55
b10 )
0!
b1 *
1"
#60
0"
#65
b10 *
1"
#70
b11 )
0#
0"
#75
b0 )
b11 *
1"
#80
1!
b1 )
1#
0"
#85
b10 )
0!
b1 *
1"
#90
b0 )
0#
0"
#95
b0 *
1"
