fsm-assignments(LAB2)/problem2_traffic/traffic_light.v
module traffic_light(
input wire clk,
input wire rst, // sync active-high
input wire tick, // 1-cycle per-second pulse
output wire ns_g, ns_y, ns_r,
output wire ew_g, ew_y, ew_r
);

reg [2:0] state_present, state_next;

wire out;
reg road = 1'b0;

parameter init = 3'b000;
parameter one = 3'b001;
parameter two = 3'b010;
parameter three = 3'b011;
parameter four = 3'b100;
parameter five = 3'b101;
parameter six = 3'b110;

always @(posedge clk) begin
    if(rst) state_present <= init;
    else state_present <= state_next;
end

always @(*) begin
    case(state_present)
        init: begin
            if(tick) state_next = one;
            else state_next = state_present;
        end
        one: begin
            if(tick) state_next = two;
            else state_next = state_present;
        end
        two: begin
            if(tick) state_next = three;
            else state_next = state_present;
        end
        three: begin
            if(tick) state_next = four;
            else state_next = state_present;
        end
        four: begin
            if(tick) state_next = five;
            else state_next = state_present;
        end
        five: begin 
            if(tick) state_next = six;
            else state_next = state_present;
        end
        six: begin 
            if(tick) state_next = init;
            else state_next = state_present;
        end
        default: state_next = state_present;
    endcase
end

assign out = (state_present == six);

always @(posedge clk) begin
    if(rst) road <= 1'b0; 
    else if(tick && (state_present == six)) road <= ~road;
end

assign ns_r = (road == 1'b1);
assign ew_r = (road == 1'b0);
assign ns_g = (road == 1'b0)&&((state_present == init)  ||
                    (state_present == one)  ||
                    (state_present == two)  ||
                    (state_present == three)||
                    (state_present == four));
assign ns_y = (road == 1'b0)&&((state_present == five)||(state_present == six));
assign ew_g = (road == 1'b1)&&((state_present == init)  ||
                    (state_present == one)  ||
                    (state_present == two)  ||
                    (state_present == three)||
                    (state_present == four));
assign ew_y = (road == 1'b1)&&((state_present == five)||(state_present == six));
endmodule

fsm-assignments(LAB2)/problem2_traffic/tb_traffic_light.v
`timescale 1ms/1ms

module tb_traffic_light;
reg clk, rst, tick;
wire ns_g, ns_y, ns_r, ew_g, ew_y, ew_r;

traffic_light dut(
.clk(clk), .rst(rst), .tick(tick),
.ns_g(ns_g), .ns_y(ns_y), .ns_r(ns_r),
.ew_g(ew_g), .ew_y(ew_y), .ew_r(ew_r)
);

initial begin
    clk = 0;
end
always #5 clk = ~clk;

initial begin
    tick = 0;
end
always begin
    #1_000 tick = 1;
    #10 tick = 0;
end


initial begin
    $dumpfile("test.vcd");
    $dumpvars(0, tb_traffic_light);
    
    rst = 1;
    #12;
    rst = 0;
    
    #20_000;
    $finish;

end

endmodule

fsm-assignments(LAB2)/problem2_traffic/test.vcd
$date
	Sun Aug 17 17:05:51 2025
$end
$version
	Icarus Verilog
$end
$timescale
	1ms
$end
$scope module tb_traffic_light $end
$var wire 1 ! ns_y $end
$var wire 1 " ns_r $end
$var wire 1 # ns_g $end
$var wire 1 $ ew_y $end
$var wire 1 % ew_r $end
$var wire 1 & ew_g $end
$var reg 1 ' clk $end
$var reg 1 ( rst $end
$var reg 1 ) tick $end
$scope module dut $end
$var wire 1 ' clk $end
$var wire 1 & ew_g $end
$var wire 1 % ew_r $end
$var wire 1 $ ew_y $end
$var wire 1 # ns_g $end
$var wire 1 " ns_r $end
$var wire 1 ! ns_y $end
$var wire 1 ( rst $end
$var wire 1 ) tick $end
$var wire 1 * out $end
$var parameter 3 + five $end
$var parameter 3 , four $end
$var parameter 3 - init $end
$var parameter 3 . one $end
$var parameter 3 / six $end
$var parameter 3 0 three $end
$var parameter 3 1 two $end
$var reg 1 2 road $end
$var reg 3 3 state_next [2:0] $end
$var reg 3 4 state_present [2:0] $end
$upscope $end
$upscope $end
$enddefinitions $end
$comment Show the parameter values. $end
$dumpall
b10 1
b11 0
b110 /
b1 .
b0 -
b100 ,
b101 +
$end
#0
$dumpvars
bx 4
bx 3
02
x*
0)
1(
0'
0&
1%
0$
x#
0"
x!
$end
#5
1#
0!
b0 3
0*
b0 4
1'
#10
0'
#12
0(
#15
1'
#20
0'
#25
1'
#30
0'
#35
1'
#40
0'
#45
1'
#50
0'
#55
1'
#60
0'
#65
1'
#70
0'
#75
1'
#80
0'
#85
1'
#90
0'
#95
1'
#100
0'
#105
1'
#110
0'
#115
1'
#120
0'
#125
1'
#130
0'
#135
1'
#140
0'
#145
1'
#150
0'
#155
1'
#160
0'
#165
1'
#170
0'
#175
1'
#180
0'
#185
1'
#190
0'
#195
1'
#200
0'
#205
1'
#210
0'
#215
1'
#220
0'
#225
1'
#230
0'
#235
1'
#240
0'
#245
1'
#250
0'
#255
1'
#260
0'
#265
1'
#270
0'
#275
1'
#280
0'
#285
1'
#290
0'
#295
1'
#300
0'
#305
1'
#310
0'
#315
1'
#320
0'
#325
1'
#330
0'
#335
1'
#340
0'
#345
1'
#350
0'
#355
1'
#360
0'
#365
1'
#370
0'
#375
1'
#380
0'
#385
1'
#390
0'
#395
1'
#400
0'
#405
1'
#410
0'
#415
1'
#420
0'
#425
1'
#430
0'
#435
1'
#440
0'
#445
1'
#450
0'
#455
1'
#460
0'
#465
1'
#470
0'
#475
1'
#480
0'
#485
1'
#490
0'
#495
1'
#500
0'
#505
1'
#510
0'
#515
1'
#520
0'
#525
1'
#530
0'
#535
1'
#540
0'
#545
1'
#550
0'
#555
1'
#560
0'
#565
1'
#570
0'
#575
1'
#580
0'
#585
1'
#590
0'
#595
1'
#600
0'
#605
1'
#610
0'
#615
1'
#620
0'
#625
1'
#630
0'
#635
1'
#640
0'
#645
1'
#650
0'
#655
1'
#660
0'
#665
1'
#670
0'
#675
1'
#680
0'
#685
1'
#690
0'
#695
1'
#700
0'
#705
1'
#710
0'
#715
1'
#720
0'
#725
1'
#730
0'
#735
1'
#740
0'
#745
1'
#750
0'
#755
1'
#760
0'
#765
1'
#770
0'
#775
1'
#780
0'
#785
1'
#790
0'
#795
1'
#800
0'
#805
1'
#810
0'
#815
1'
#820
0'
#825
1'
#830
0'
#835
1'
#840
0'
#845
1'
#850
0'
#855
1'
#860
0'
#865
1'
#870
0'
#875
1'
#880
0'
#885
1'
#890
0'
#895
1'
#900
0'
#905
1'
#910
0'
#915
1'
#920
0'
#925
1'
#930
0'
#935
1'
#940
0'
#945
1'
#950
0'
#955
1'
#960
0'
#965
1'
#970
0'
#975
1'
#980
0'
#985
1'
#990
0'
#995
1'
#1000
b1 3
0'
1)
#1005
b10 3
b1 4
1'
#1010
b1 3
0'
0)
#1015
1'
#1020
0'
#1025
1'
#1030
0'
#1035
1'
#1040
0'
#1045
1'
#1050
0'
#1055
1'
#1060
0'
#1065
1'
#1070
0'
#1075
1'
#1080
0'
#1085
1'
#1090
0'
#1095
1'
#1100
0'
#1105
1'
#1110
0'
#1115
1'
#1120
0'
#1125
1'
#1130
0'
#1135
1'
#1140
0'
#1145
1'
#1150
0'
#1155
1'
#1160
0'
#1165
1'
#1170
0'
#1175
1'
#1180
0'
#1185
1'
#1190
0'
#1195
1'
#1200
0'
#1205
1'
#1210
0'
#1215
1'
#1220
0'
#1225
1'
#1230
0'
#1235
1'
#1240
0'
#1245
1'
#1250
0'
#1255
1'
#1260
0'
#1265
1'
#1270
0'
#1275
1'
#1280
0'
#1285
1'
#1290
0'
#1295
1'
#1300
0'
#1305
1'
#1310
0'
#1315
1'
#1320
0'
#1325
1'
#1330
0'
#1335
1'
#1340
0'
#1345
1'
#1350
0'
#1355
1'
#1360
0'
#1365
1'
#1370
0'
#1375
1'
#1380
0'
#1385
1'
#1390
0'
#1395
1'
#1400
0'
#1405
1'
#1410
0'
#1415
1'
#1420
0'
#1425
1'
#1430
0'
#1435
1'
#1440
0'
#1445
1'
#1450
0'
#1455
1'
#1460
0'
#1465
1'
#1470
0'
#1475
1'
#1480
0'
#1485
1'
#1490
0'
#1495
1'
#1500
0'
#1505
1'
#1510
0'
#1515
1'
#1520
0'
#1525
1'
#1530
0'
#1535
1'
#1540
0'
#1545
1'
#1550
0'
#1555
1'
#1560
0'
#1565
1'
#1570
0'
#1575
1'
#1580
0'
#1585
1'
#1590
0'
#1595
1'
#1600
0'
#1605
1'
#1610
0'
#1615
1'
#1620
0'
#1625
1'
#1630
0'
#1635
1'
#1640
0'
#1645
1'
#1650
0'
#1655
1'
#1660
0'
#1665
1'
#1670
0'
#1675
1'
#1680
0'
#1685
1'
#1690
0'
#1695
1'
#1700
0'
#1705
1'
#1710
0'
#1715
1'
#1720
0'
#1725
1'
#1730
0'
#1735
1'
#1740
0'
#1745
1'
#1750
0'
#1755
1'
#1760
0'
#1765
1'
#1770
0'
#1775
1'
#1780
0'
#1785
1'
#1790
0'
#1795
1'
#1800
0'
#1805
1'
#1810
0'
#1815
1'
#1820
0'
#1825
1'
#1830
0'
#1835
1'
#1840
0'
#1845
1'
#1850
0'
#1855
1'
#1860
0'
#1865
1'
#1870
0'
#1875
1'
#1880
0'
#1885
1'
#1890
0'
#1895
1'
#1900
0'
#1905
1'
#1910
0'
#1915
1'
#1920
0'
#1925
1'
#1930
0'
#1935
1'
#1940
0'
#1945
1'
#1950
0'
#1955
1'
#1960
0'
#1965
1'
#1970
0'
#1975
1'
#1980
0'
#1985
1'
#1990
0'
#1995
1'
#2000
0'
#2005
1'
#2010
b10 3
0'
1)
#2015
b11 3
b10 4
1'
#2020
b10 3
0'
0)
